stock_report/__init__.py
stock_report/__main__.py
stock_report/analysis.py
stock_report/data.py
stock_report/pdf.py
stock_report/resources/__init__.py
stock_report/resources/footer.png
stock_report/resources/header.png
stock_report/resources/logo.png
stock_report-1.0.0.dist-info/LICENSE
stock_report-1.0.0.dist-info/METADATA
stock_report-1.0.0.dist-info/WHEEL
stock_report-1.0.0.dist-info/top_level.txt
stock_report-1.0.0.dist-info/RECORD
