Metadata-Version: 2.1
Name: stock-report
Version: 1.0.0
Summary: StockReport is a Python program that allows you to simply create an automated PDF report about a stock.
Home-page: https://github.com/pfeiffer-dev/stock-report
Author: Kevin Pfeiffer
Author-email: pfeiffer.kevin@gmx.de
License: UNKNOWN
Project-URL: Bug Reports, https://github.com/pfeiffer-dev/stock-report/issues
Project-URL: Source, https://github.com/pfeiffer-dev/stock-report
Keywords: stock-market,pandas,pdf,report,fpdf,alpha-vantage,plotly-express
Platform: UNKNOWN
Classifier: Development Status :: 5 - Production/Stable
Classifier: Topic :: Office/Business :: Financial :: Investment
Classifier: License :: OSI Approved :: MIT License
Classifier: Programming Language :: Python :: 3
Classifier: Operating System :: OS Independent
Classifier: Natural Language :: English
Requires-Python: >=3.6
License-File: LICENSE
Requires-Dist: alpha-vantage
Requires-Dist: pandas
Requires-Dist: fpdf
Requires-Dist: plotly
Requires-Dist: kaleido
